<?xml version="1.0"?>
<odoo>

	<record id="view_delivery_carrier_form" model="ir.ui.view">
        <field name="name">delivery.carrier.form</field>
        <field name="model">delivery.carrier</field>
        <field name="type">form</field>
        <field name="inherit_id" ref="delivery.view_delivery_carrier_form" />
        <field name="arch" type="xml">
             <notebook  position="inside">
              <page string="Fedex">
                    <group name="Fedex" string="fedex"
                    	>
                       <field name="account_no"/>
                       <field name="meter_no"/>
                       <field name="integration_id"/>
                       <field name="fedex_key"/>
                       <field name="fedex_password"/>
                    </group>
            </page>
            </notebook>
        </field>
    </record>
</odoo>
